Metadata-Version: 2.4
Name: strata-mcp
Version: 1.0.1
Summary: One Model Context Protocol (MCP) server for AI agents to handle thousands of tools
Project-URL: Homepage, https://github.com/Klavis-AI/klavis
Project-URL: Repository, https://github.com/Klavis-AI/klavis.git
Project-URL: Issues, https://github.com/Klavis-AI/klavis/issues
Author-email: Klavis AI <connect@klavis.ai>
License: Apache-2.0
License-File: LICENSE
Keywords: ai,llm,mcp,model-context-protocol,router,tools
Classifier: Development Status :: 5 - Production/Stable
Classifier: Intended Audience :: Developers
Classifier: License :: OSI Approved :: Apache Software License
Classifier: Operating System :: OS Independent
Classifier: Programming Language :: Python :: 3
Classifier: Programming Language :: Python :: 3.10
Classifier: Programming Language :: Python :: 3.11
Classifier: Programming Language :: Python :: 3.12
Classifier: Programming Language :: Python :: 3.13
Classifier: Topic :: Communications
Classifier: Topic :: Scientific/Engineering :: Artificial Intelligence
Classifier: Topic :: Software Development :: Libraries :: Python Modules
Classifier: Topic :: System :: Distributed Computing
Requires-Python: >=3.10
Requires-Dist: bm25s>=0.2.14
Requires-Dist: mcp>=1.0.0
Requires-Dist: platformdirs>=4.4.0
Requires-Dist: pystemmer>=3.0.0
Requires-Dist: starlette>=0.37.0
Requires-Dist: uvicorn>=0.30.0
Requires-Dist: watchgod>=0.7
Provides-Extra: dev
Requires-Dist: pytest-asyncio>=0.21.0; extra == 'dev'
Requires-Dist: pytest>=7.0.0; extra == 'dev'
